venusianconfiguration/__init__.py
venusianconfiguration/directives.py
venusianconfiguration/meta.py
venusianconfiguration/tests/__init__.py
venusianconfiguration/tests/test_configuremeta.py
venusianconfiguration-1.1.2.dist-info/METADATA
venusianconfiguration-1.1.2.dist-info/WHEEL
venusianconfiguration-1.1.2.dist-info/namespace_packages.txt
venusianconfiguration-1.1.2.dist-info/top_level.txt
venusianconfiguration-1.1.2.dist-info/RECORD
