Metadata-Version: 2.1
Name: venusianconfiguration
Version: 1.1.2
Summary: Experiment for configuring with venusian instead of *.zcml
Home-page: https://github.com/datakurre/venusianconfiguration/
Author: Asko Soukka
Author-email: asko.soukka@iki.fi
License: GPL
Platform: UNKNOWN
Classifier: Programming Language :: Python
Requires-Dist: setuptools
Requires-Dist: six
Requires-Dist: zope.configuration
Requires-Dist: venusian (>=1.0a8)
Provides-Extra: test
Requires-Dist: plone.testing ; extra == 'test'
